gender_guess_indian/__init__.py
gender_guess_indian/guess_gender.py
gender_guess_indian/tests/__init__.py
gender_guess_indian/tests/test_guess_gender.py
guess_indian_gender/__init__.py
guess_indian_gender/guess_gender.py
guess_indian_gender/data/Indian-Female-Names.csv
guess_indian_gender/data/Indian-Male-Names.csv
guess_indian_gender/tests/__init__.py
guess_indian_gender/tests/test_guess_gender.py
guess_indian_gender-1.0.1.dist-info/LICENSE
guess_indian_gender-1.0.1.dist-info/METADATA
guess_indian_gender-1.0.1.dist-info/WHEEL
guess_indian_gender-1.0.1.dist-info/top_level.txt
guess_indian_gender-1.0.1.dist-info/RECORD
