Metadata-Version: 2.1
Name: guess-indian-gender
Version: 1.0.1
Summary: Guess gender from indian names
Home-page: https://github.com/v-adhithyan/gender-guess-indiannames
Author: v-adhithyan
Author-email: pollachi.developer@gmail.com
License: MIT
Platform: UNKNOWN
Classifier: Programming Language :: Python :: 3.7
Classifier: License :: OSI Approved :: MIT License
Classifier: Operating System :: OS Independent
Requires-Dist: nltk
Requires-Dist: pandas
